hellosp/__init__.py
hellosp/cli.py
hellosp-0.3.0.dist-info/LICENSE.txt
hellosp-0.3.0.dist-info/METADATA
hellosp-0.3.0.dist-info/WHEEL
hellosp-0.3.0.dist-info/entry_points.txt
hellosp-0.3.0.dist-info/top_level.txt
hellosp-0.3.0.dist-info/RECORD
