Metadata-Version: 2.1
Name: hellosp
Version: 0.3.0
Summary: This is a simple cli to calculate the sum of 2 numbers
Home-page: UNKNOWN
Author: Shanmuga Priya
Author-email: shanmugapriya.rs@embedur.com
License: UNKNOWN
Platform: UNKNOWN
Classifier: Programming Language :: Python :: 3
Classifier: License :: OSI Approved :: MIT License
Classifier: Operating System :: OS Independent
Requires-Python: >=3.6
